{
	  "description": "Learning Resources Schema", 
	  "fields": [
		{
		  "@context": "https://schema.org/",
		  "@type": "CreativeWork",
		  "name": "abstract",
		  "name": "abstract_data", 
		  "type": "General Text", 
		  "multivalue": false, 
		  "required": true,
		  "title": "Description",
		  "definition": "A brief synopsis or abstract about the learning resource",
		  "scopeNotes":"",
		  "controlledVocabulary": {
			"source":"",
			"terms":[
				{
					"term":"",
					"mapsTo": {
						"term": "",
						"source": "",
						"relationship": ""
					}
				}
			]  
		  }
		},
		...
}
